README.rst
setup.py
FastTextRank/FastTextRank4Sentence.py
FastTextRank/FastTextRank4Word.py
FastTextRank/__init__.py
FastTextRank/util.py
FastTextRank.egg-info/PKG-INFO
FastTextRank.egg-info/SOURCES.txt
FastTextRank.egg-info/dependency_links.txt
FastTextRank.egg-info/requires.txt
FastTextRank.egg-info/top_level.txt